{
  "per_template": {
    "0": {
      "tau": 0.529,
      "tau_score_curve": {
        "0.4598": 0.1596,
        "0.4996": 0.2279,
        "0.529": 0.25,
        "0.5727": 0.2279,
        "0.6154": 0.1596
      },
      "cka_mean": 0.9116,
      "ged_mean": 0.4574,
      "ber": 0.0449,
      "per_style_cka": {
        "angrily": 0.8867,
        "tiredly": 0.8981,
        "happily": 0.9106,
        "nervously": 0.8811,
        "gracefully": 0.9196,
        "heavily": 0.9324,
        "confidently": 0.9255,
        "carefully": 0.9184,
        "casually": 0.9356,
        "gently": 0.9226,
        "cautiously": 0.888,
        "calmly": 0.9159,
        "aggressively": 0.9169
      },
      "per_style_cka_p": {
        "angrily": 0.0,
        "tiredly": 0.0,
        "happily": 0.0,
        "nervously": 0.0,
        "gracefully": 0.0,
        "heavily": 0.0,
        "confidently": 0.0,
        "carefully": 0.0,
        "casually": 0.0,
        "gently": 0.0,
        "cautiously": 0.0,
        "calmly": 0.0,
        "aggressively": 0.0
      },
      "per_style_ged": {
        "angrily": 0.5,
        "tiredly": 0.5,
        "happily": 0.4312,
        "nervously": 0.5,
        "gracefully": 0.4384,
        "heavily": 0.4964,
        "confidently": 0.4529,
        "carefully": 0.4529,
        "casually": 0.3587,
        "gently": 0.4384,
        "cautiously": 0.4674,
        "calmly": 0.4203,
        "aggressively": 0.4891
      },
      "per_style_ged_p": {
        "angrily": 1.0,
        "tiredly": 1.0,
        "happily": 1.0,
        "nervously": 1.0,
        "gracefully": 1.0,
        "heavily": 1.0,
        "confidently": 1.0,
        "carefully": 1.0,
        "casually": 1.0,
        "gently": 1.0,
        "cautiously": 1.0,
        "calmly": 1.0,
        "aggressively": 1.0
      },
      "escape_matrix": [
        [
          0,
          0,
          0,
          0,
          0,
          0,
          0,
          0,
          0,
          0,
          0,
          0,
          1,
          0,
          0,
          0,
          0,
          0,
          0,
          0,
          0,
          0,
          1,
          0
        ],
        [
          0,
          1,
          0,
          0,
          0,
          0,
          0,
          0,
          0,
          0,
          0,
          0,
          0,
          0,
          0,
          0,
          0,
          0,
          0,
          0,
          0,
          0,
          0,
          0
        ],
        [
          0,
          0,
          0,
          0,
          0,
          0,
          0,
          0,
          0,
          0,
          0,
          0,
          0,
          0,
          0,
          0,
          0,
          0,
          0,
          0,
          0,
          0,
          0,
          0
        ],
        [
          0,
          1,
          0,
          0,
          0,
          0,
          0,
          0,
          0,
          0,
          0,
          0,
          0,
          0,
          0,
          1,
          0,
          0,
          0,
          0,
          0,
          0,
          1,
          0
        ],
        [
          0,
          0,
          0,
          0,
          0,
          0,
          0,
          0,
          0,
          0,
          0,
          0,
          0,
          0,
          0,
          0,
          0,
          0,
          0,
          0,
          0,
          0,
          0,
          0
        ],
        [
          0,
          0,
          0,
          0,
          0,
          0,
          0,
          0,
          0,
          0,
          0,
          0,
          0,
          0,
          0,
          0,
          0,
          0,
          0,
          1,
          0,
          0,
          0,
          0
        ],
        [
          0,
          1,
          0,
          0,
          0,
          0,
          0,
          0,
          0,
          0,
          0,
          0,
          0,
          0,
          0,
          0,
          0,
          0,
          0,
          0,
          0,
          0,
          0,
          0
        ],
        [
          0,
          0,
          0,
          0,
          0,
          0,
          0,
          0,
          0,
          0,
          0,
          0,
          0,
          0,
          0,
          0,
          0,
          0,
          0,
          0,
          0,
          0,
          0,
          0
        ],
        [
          0,
          0,
          0,
          0,
          0,
          0,
          0,
          0,
          0,
          0,
          0,
          0,
          0,
          0,
          0,
          0,
          0,
          0,
          0,
          0,
          0,
          0,
          0,
          0
        ],
        [
          0,
          1,
          0,
          0,
          0,
          0,
          0,
          0,
          0,
          0,
          0,
          0,
          0,
          0,
          0,
          0,
          0,
          0,
          0,
          0,
          0,
          0,
          0,
          0
        ],
        [
          1,
          1,
          0,
          0,
          0,
          0,
          1,
          0,
          0,
          0,
          0,
          0,
          0,
          0,
          0,
          1,
          0,
          0,
          0,
          1,
          0,
          0,
          0,
          0
        ],
        [
          0,
          0,
          0,
          0,
          0,
          0,
          0,
          0,
          0,
          0,
          0,
          0,
          0,
          0,
          0,
          0,
          0,
          0,
          0,
          0,
          0,
          0,
          0,
          0
        ],
        [
          0,
          0,
          0,
          0,
          0,
          0,
          0,
          0,
          0,
          0,
          0,
          0,
          0,
          0,
          0,
          0,
          0,
          0,
          0,
          0,
          0,
          0,
          0,
          0
        ]
      ],
      "consistency": {
        "angrily": 0.4229,
        "tiredly": 0.4315,
        "happily": 0.3751,
        "nervously": 0.4704,
        "gracefully": 0.36,
        "heavily": 0.4079,
        "confidently": 0.3763,
        "carefully": 0.4046,
        "casually": 0.3402,
        "gently": 0.3738,
        "cautiously": 0.389,
        "calmly": 0.3892,
        "aggressively": 0.3714
      },
      "consistency_p": {
        "angrily": 0.0,
        "tiredly": 0.0,
        "happily": 0.0,
        "nervously": 0.0,
        "gracefully": 0.0,
        "heavily": 0.0,
        "confidently": 0.0,
        "carefully": 0.0,
        "casually": 0.0,
        "gently": 0.0,
        "cautiously": 0.0,
        "calmly": 0.0,
        "aggressively": 0.0
      },
      "consistency_mean": 0.3932,
      "delta_rel_magnitude": 0.5859
    },
    "1": {
      "tau": 0.529,
      "tau_score_curve": {
        "0.4598": 0.1596,
        "0.4996": 0.2279,
        "0.529": 0.25,
        "0.5727": 0.2279,
        "0.6154": 0.1596
      },
      "cka_mean": 0.9149,
      "ged_mean": 0.4844,
      "ber": 0.0353,
      "per_style_cka": {
        "angrily": 0.8885,
        "tiredly": 0.9078,
        "happily": 0.9266,
        "nervously": 0.9071,
        "gracefully": 0.9249,
        "heavily": 0.8752,
        "confidently": 0.9329,
        "carefully": 0.9206,
        "casually": 0.9251,
        "gently": 0.9308,
        "cautiously": 0.8953,
        "calmly": 0.9432,
        "aggressively": 0.9163
      },
      "per_style_cka_p": {
        "angrily": 0.0,
        "tiredly": 0.0,
        "happily": 0.0,
        "nervously": 0.0,
        "gracefully": 0.0,
        "heavily": 0.0,
        "confidently": 0.0,
        "carefully": 0.0,
        "casually": 0.0,
        "gently": 0.0,
        "cautiously": 0.0,
        "calmly": 0.0,
        "aggressively": 0.0
      },
      "per_style_ged": {
        "angrily": 0.5,
        "tiredly": 0.5,
        "happily": 0.471,
        "nervously": 0.5,
        "gracefully": 0.4891,
        "heavily": 0.4964,
        "confidently": 0.4964,
        "carefully": 0.471,
        "casually": 0.4746,
        "gently": 0.4457,
        "cautiously": 0.4964,
        "calmly": 0.4601,
        "aggressively": 0.4964
      },
      "per_style_ged_p": {
        "angrily": 1.0,
        "tiredly": 1.0,
        "happily": 1.0,
        "nervously": 1.0,
        "gracefully": 1.0,
        "heavily": 1.0,
        "confidently": 1.0,
        "carefully": 1.0,
        "casually": 1.0,
        "gently": 1.0,
        "cautiously": 1.0,
        "calmly": 1.0,
        "aggressively": 1.0
      },
      "escape_matrix": [
        [
          0,
          0,
          0,
          0,
          0,
          0,
          0,
          0,
          0,
          1,
          0,
          0,
          1,
          0,
          0,
          0,
          0,
          0,
          0,
          1,
          0,
          0,
          0,
          0
        ],
        [
          0,
          0,
          0,
          0,
          0,
          0,
          0,
          0,
          0,
          0,
          0,
          0,
          0,
          0,
          0,
          0,
          0,
          0,
          0,
          1,
          0,
          0,
          0,
          0
        ],
        [
          0,
          0,
          0,
          0,
          0,
          0,
          0,
          0,
          0,
          0,
          0,
          0,
          0,
          0,
          0,
          0,
          0,
          0,
          0,
          0,
          0,
          0,
          0,
          0
        ],
        [
          1,
          1,
          0,
          0,
          0,
          0,
          0,
          0,
          0,
          0,
          0,
          0,
          0,
          0,
          0,
          0,
          0,
          0,
          0,
          0,
          0,
          0,
          1,
          0
        ],
        [
          0,
          0,
          0,
          0,
          0,
          0,
          0,
          0,
          0,
          0,
          0,
          0,
          0,
          0,
          0,
          0,
          0,
          0,
          0,
          0,
          0,
          0,
          0,
          0
        ],
        [
          0,
          0,
          0,
          0,
          0,
          0,
          0,
          0,
          0,
          0,
          0,
          0,
          1,
          0,
          0,
          0,
          0,
          0,
          0,
          1,
          0,
          0,
          0,
          0
        ],
        [
          0,
          0,
          0,
          0,
          0,
          0,
          0,
          0,
          0,
          0,
          0,
          0,
          0,
          0,
          0,
          0,
          0,
          0,
          0,
          0,
          0,
          0,
          0,
          0
        ],
        [
          0,
          0,
          0,
          0,
          0,
          0,
          0,
          0,
          0,
          0,
          0,
          0,
          0,
          0,
          0,
          0,
          0,
          0,
          0,
          0,
          0,
          0,
          0,
          0
        ],
        [
          0,
          0,
          0,
          0,
          0,
          0,
          0,
          0,
          0,
          0,
          0,
          0,
          0,
          0,
          0,
          0,
          0,
          0,
          0,
          0,
          0,
          0,
          0,
          0
        ],
        [
          0,
          0,
          0,
          0,
          0,
          0,
          0,
          0,
          0,
          0,
          0,
          0,
          0,
          0,
          0,
          0,
          0,
          0,
          0,
          0,
          0,
          0,
          0,
          0
        ],
        [
          0,
          1,
          0,
          0,
          0,
          0,
          0,
          0,
          0,
          0,
          0,
          0,
          0,
          0,
          0,
          0,
          0,
          0,
          0,
          0,
          0,
          0,
          0,
          0
        ],
        [
          0,
          0,
          0,
          0,
          0,
          0,
          0,
          0,
          0,
          0,
          0,
          0,
          0,
          0,
          0,
          0,
          0,
          0,
          0,
          0,
          0,
          0,
          0,
          0
        ],
        [
          0,
          0,
          0,
          0,
          0,
          0,
          0,
          0,
          0,
          0,
          0,
          0,
          1,
          0,
          0,
          0,
          0,
          0,
          0,
          0,
          0,
          0,
          0,
          0
        ]
      ],
      "consistency": {
        "angrily": 0.4496,
        "tiredly": 0.4406,
        "happily": 0.4044,
        "nervously": 0.464,
        "gracefully": 0.3548,
        "heavily": 0.4198,
        "confidently": 0.3702,
        "carefully": 0.3979,
        "casually": 0.3832,
        "gently": 0.3834,
        "cautiously": 0.4308,
        "calmly": 0.4095,
        "aggressively": 0.4121
      },
      "consistency_p": {
        "angrily": 0.0,
        "tiredly": 0.0,
        "happily": 0.0,
        "nervously": 0.0,
        "gracefully": 0.0,
        "heavily": 0.0,
        "confidently": 0.0,
        "carefully": 0.0,
        "casually": 0.0,
        "gently": 0.0,
        "cautiously": 0.0,
        "calmly": 0.0,
        "aggressively": 0.0
      },
      "consistency_mean": 0.4092,
      "delta_rel_magnitude": 0.5711
    },
    "2": {
      "tau": 0.4913,
      "tau_score_curve": {
        "0.4135": 0.1617,
        "0.4553": 0.2279,
        "0.4913": 0.25,
        "0.5305": 0.2279,
        "0.5684": 0.1596
      },
      "cka_mean": 0.8973,
      "ged_mean": 0.4824,
      "ber": 0.0801,
      "per_style_cka": {
        "angrily": 0.8663,
        "tiredly": 0.8878,
        "happily": 0.8966,
        "nervously": 0.9018,
        "gracefully": 0.8916,
        "heavily": 0.9109,
        "confidently": 0.9108,
        "carefully": 0.9059,
        "casually": 0.9183,
        "gently": 0.8968,
        "cautiously": 0.886,
        "calmly": 0.9117,
        "aggressively": 0.8808
      },
      "per_style_cka_p": {
        "angrily": 0.0,
        "tiredly": 0.0,
        "happily": 0.0,
        "nervously": 0.0,
        "gracefully": 0.0,
        "heavily": 0.0,
        "confidently": 0.0,
        "carefully": 0.0,
        "casually": 0.0,
        "gently": 0.0,
        "cautiously": 0.0,
        "calmly": 0.0,
        "aggressively": 0.0
      },
      "per_style_ged": {
        "angrily": 0.5,
        "tiredly": 0.4819,
        "happily": 0.4819,
        "nervously": 0.5,
        "gracefully": 0.5,
        "heavily": 0.4746,
        "confidently": 0.4855,
        "carefully": 0.4891,
        "casually": 0.4348,
        "gently": 0.4674,
        "cautiously": 0.5,
        "calmly": 0.4674,
        "aggressively": 0.4891
      },
      "per_style_ged_p": {
        "angrily": 1.0,
        "tiredly": 1.0,
        "happily": 1.0,
        "nervously": 1.0,
        "gracefully": 1.0,
        "heavily": 1.0,
        "confidently": 1.0,
        "carefully": 1.0,
        "casually": 1.0,
        "gently": 1.0,
        "cautiously": 1.0,
        "calmly": 1.0,
        "aggressively": 1.0
      },
      "escape_matrix": [
        [
          0,
          0,
          0,
          0,
          0,
          1,
          0,
          0,
          0,
          0,
          0,
          0,
          0,
          0,
          0,
          0,
          0,
          0,
          0,
          1,
          0,
          0,
          0,
          0
        ],
        [
          1,
          0,
          0,
          0,
          0,
          0,
          0,
          0,
          0,
          1,
          0,
          0,
          0,
          0,
          0,
          0,
          0,
          0,
          0,
          1,
          0,
          0,
          0,
          0
        ],
        [
          1,
          0,
          0,
          0,
          0,
          1,
          0,
          0,
          0,
          0,
          0,
          0,
          0,
          0,
          0,
          0,
          0,
          0,
          0,
          1,
          0,
          0,
          0,
          0
        ],
        [
          0,
          0,
          0,
          0,
          0,
          0,
          0,
          0,
          0,
          1,
          0,
          0,
          0,
          0,
          0,
          0,
          0,
          0,
          0,
          0,
          0,
          0,
          0,
          0
        ],
        [
          0,
          0,
          0,
          0,
          0,
          0,
          0,
          0,
          0,
          1,
          0,
          0,
          0,
          0,
          0,
          0,
          0,
          0,
          0,
          0,
          0,
          0,
          0,
          0
        ],
        [
          1,
          0,
          0,
          0,
          0,
          0,
          0,
          0,
          0,
          0,
          0,
          0,
          0,
          0,
          0,
          0,
          0,
          0,
          0,
          1,
          0,
          0,
          0,
          0
        ],
        [
          0,
          0,
          0,
          0,
          0,
          1,
          0,
          0,
          0,
          0,
          0,
          0,
          0,
          0,
          0,
          0,
          0,
          0,
          0,
          1,
          0,
          0,
          0,
          0
        ],
        [
          0,
          1,
          0,
          0,
          0,
          0,
          0,
          0,
          0,
          0,
          0,
          0,
          0,
          0,
          0,
          0,
          0,
          0,
          0,
          1,
          0,
          0,
          0,
          0
        ],
        [
          0,
          0,
          0,
          0,
          0,
          0,
          0,
          0,
          0,
          0,
          0,
          0,
          0,
          0,
          0,
          0,
          0,
          0,
          0,
          0,
          0,
          0,
          0,
          0
        ],
        [
          0,
          1,
          0,
          0,
          0,
          0,
          0,
          0,
          0,
          1,
          0,
          0,
          0,
          0,
          0,
          0,
          0,
          0,
          0,
          1,
          0,
          0,
          0,
          0
        ],
        [
          0,
          1,
          0,
          0,
          0,
          1,
          0,
          0,
          0,
          1,
          0,
          0,
          0,
          0,
          0,
          0,
          0,
          0,
          0,
          1,
          0,
          0,
          0,
          0
        ],
        [
          1,
          0,
          0,
          0,
          0,
          0,
          0,
          0,
          0,
          0,
          0,
          0,
          0,
          0,
          0,
          0,
          0,
          0,
          0,
          1,
          0,
          0,
          0,
          0
        ],
        [
          0,
          0,
          0,
          0,
          0,
          0,
          0,
          0,
          0,
          0,
          0,
          0,
          0,
          0,
          0,
          0,
          0,
          0,
          0,
          0,
          0,
          0,
          0,
          0
        ]
      ],
      "consistency": {
        "angrily": 0.418,
        "tiredly": 0.4483,
        "happily": 0.4151,
        "nervously": 0.3857,
        "gracefully": 0.4427,
        "heavily": 0.4091,
        "confidently": 0.3903,
        "carefully": 0.4176,
        "casually": 0.3776,
        "gently": 0.4092,
        "cautiously": 0.4284,
        "calmly": 0.4223,
        "aggressively": 0.4184
      },
      "consistency_p": {
        "angrily": 0.0,
        "tiredly": 0.0,
        "happily": 0.0,
        "nervously": 0.0,
        "gracefully": 0.0,
        "heavily": 0.0,
        "confidently": 0.0,
        "carefully": 0.0,
        "casually": 0.0,
        "gently": 0.0,
        "cautiously": 0.0,
        "calmly": 0.0,
        "aggressively": 0.0
      },
      "consistency_mean": 0.414,
      "delta_rel_magnitude": 0.6461
    }
  },
  "summary": {
    "angrily": {
      "cka_mean": 0.8805,
      "cka_std": 0.0101,
      "ged_mean": 0.5,
      "ged_std": 0.0
    },
    "tiredly": {
      "cka_mean": 0.8979,
      "cka_std": 0.0082,
      "ged_mean": 0.494,
      "ged_std": 0.0085
    },
    "happily": {
      "cka_mean": 0.9113,
      "cka_std": 0.0123,
      "ged_mean": 0.4614,
      "ged_std": 0.0218
    },
    "nervously": {
      "cka_mean": 0.8967,
      "cka_std": 0.0112,
      "ged_mean": 0.5,
      "ged_std": 0.0
    },
    "gracefully": {
      "cka_mean": 0.912,
      "cka_std": 0.0146,
      "ged_mean": 0.4758,
      "ged_std": 0.0268
    },
    "heavily": {
      "cka_mean": 0.9062,
      "cka_std": 0.0236,
      "ged_mean": 0.4891,
      "ged_std": 0.0103
    },
    "confidently": {
      "cka_mean": 0.9231,
      "cka_std": 0.0092,
      "ged_mean": 0.4783,
      "ged_std": 0.0185
    },
    "carefully": {
      "cka_mean": 0.915,
      "cka_std": 0.0065,
      "ged_mean": 0.471,
      "ged_std": 0.0148
    },
    "casually": {
      "cka_mean": 0.9263,
      "cka_std": 0.0071,
      "ged_mean": 0.4227,
      "ged_std": 0.0481
    },
    "gently": {
      "cka_mean": 0.9167,
      "cka_std": 0.0145,
      "ged_mean": 0.4505,
      "ged_std": 0.0123
    },
    "cautiously": {
      "cka_mean": 0.8898,
      "cka_std": 0.004,
      "ged_mean": 0.4879,
      "ged_std": 0.0146
    },
    "calmly": {
      "cka_mean": 0.9236,
      "cka_std": 0.014,
      "ged_mean": 0.4493,
      "ged_std": 0.0207
    },
    "aggressively": {
      "cka_mean": 0.9047,
      "cka_std": 0.0169,
      "ged_mean": 0.4915,
      "ged_std": 0.0034
    }
  }
}